poetry_click_helloworld/__init__.py
poetry_click_helloworld/main.py
poetry_click_helloworld-0.1.0.dist-info/entry_points.txt
poetry_click_helloworld-0.1.0.dist-info/WHEEL
poetry_click_helloworld-0.1.0.dist-info/METADATA
poetry_click_helloworld-0.1.0.dist-info/RECORD
