Metadata-Version: 2.1
Name: poetry-click-helloworld
Version: 0.1.0
Summary: 
Author: Michael Ramos
Author-email: michaeltramos@protonmail.com
Requires-Python: >=3.10,<4.0
Classifier: Programming Language :: Python :: 3
Classifier: Programming Language :: Python :: 3.10
Requires-Dist: click (>=8.1.3,<9.0.0)
